{
    "initial": {
        "inputs": {
            "0": {
                "location": "RBP", 
                "size": "0x8", 
                "value": "0xb196413cd101120e"
            }, 
            "1": {
                "location": "mem_0x0", 
                "size": "0x8", 
                "value": "0x0"
            }, 
            "2": {
                "location": "mem_0x1", 
                "size": "0x8", 
                "value": "0x0"
            }, 
            "3": {
                "location": "mem_0x2", 
                "size": "0x4", 
                "value": "0x0"
            }
        }, 
        "outputs": {
            "0": {
                "location": "RAX", 
                "size": "0x8", 
                "value": "0x0"
            }, 
            "1": {
                "location": "EAX", 
                "size": "0x4", 
                "value": "0x0"
            }, 
            "2": {
                "location": "RDX", 
                "size": "0x8", 
                "value": "0x0"
            }, 
            "3": {
                "location": "mem_0xb196413cd101044e", 
                "size": "0x8", 
                "value": "0x1"
            }, 
            "4": {
                "location": "mem_0x0", 
                "size": "0x8", 
                "value": "0x0"
            }
        }
    }, 
    "sampling": {
        "0": {
            "inputs": {
                "0": {
                    "location": "RBP", 
                    "size": "0x8", 
                    "value": "0xb84a9f81b1582d4"
                }, 
                "1": {
                    "location": "mem_0x0", 
                    "size": "0x8", 
                    "value": "0x46a512ddb2cd6e75"
                }, 
                "2": {
                    "location": "mem_0x1", 
                    "size": "0x8", 
                    "value": "0xb73f25775bce29e9"
                }, 
                "3": {
                    "location": "mem_0x2", 
                    "size": "0x4", 
                    "value": "0xce50a51d"
                }
            }, 
            "outputs": {
                "0": {
                    "location": "RAX", 
                    "size": "0x8", 
                    "value": "0xb73f25775bce29e9"
                }, 
                "1": {
                    "location": "EAX", 
                    "size": "0x4", 
                    "value": "0x5bce29e9"
                }, 
                "2": {
                    "location": "RDX", 
                    "size": "0x8", 
                    "value": "0xffffffffce50a51d"
                }, 
                "3": {
                    "location": "mem_0xb84a9f81b157514", 
                    "size": "0x8", 
                    "value": "0x46a512ddb2cd6e76"
                }, 
                "4": {
                    "location": "mem_0xb73f25775bce29e9", 
                    "size": "0x8", 
                    "value": "0xffffffffce50a51d"
                }
            }
        }, 
        "1": {
            "inputs": {
                "0": {
                    "location": "RBP", 
                    "size": "0x8", 
                    "value": "0x12b1bc740fbaacf1"
                }, 
                "1": {
                    "location": "mem_0x0", 
                    "size": "0x8", 
                    "value": "0xac6464d0a97dfcf1"
                }, 
                "2": {
                    "location": "mem_0x1", 
                    "size": "0x8", 
                    "value": "0x26b703c2ae16951a"
                }, 
                "3": {
                    "location": "mem_0x2", 
                    "size": "0x4", 
                    "value": "0x586009cb"
                }
            }, 
            "outputs": {
                "0": {
                    "location": "RAX", 
                    "size": "0x8", 
                    "value": "0x26b703c2ae16951a"
                }, 
                "1": {
                    "location": "EAX", 
                    "size": "0x4", 
                    "value": "0xae16951a"
                }, 
                "2": {
                    "location": "RDX", 
                    "size": "0x8", 
                    "value": "0x586009cb"
                }, 
                "3": {
                    "location": "mem_0x12b1bc740fba9f31", 
                    "size": "0x8", 
                    "value": "0xac6464d0a97dfcf2"
                }, 
                "4": {
                    "location": "mem_0x26b703c2ae16951a", 
                    "size": "0x8", 
                    "value": "0x586009cb"
                }
            }
        }, 
        "2": {
            "inputs": {
                "0": {
                    "location": "RBP", 
                    "size": "0x8", 
                    "value": "0xe275d92226ec1404"
                }, 
                "1": {
                    "location": "mem_0x0", 
                    "size": "0x8", 
                    "value": "0x3f280a531e2a158f"
                }, 
                "2": {
                    "location": "mem_0x1", 
                    "size": "0x8", 
                    "value": "0x2e605deaee76b33b"
                }, 
                "3": {
                    "location": "mem_0x2", 
                    "size": "0x4", 
                    "value": "0x309d0e9f"
                }
            }, 
            "outputs": {
                "0": {
                    "location": "RAX", 
                    "size": "0x8", 
                    "value": "0x2e605deaee76b33b"
                }, 
                "1": {
                    "location": "EAX", 
                    "size": "0x4", 
                    "value": "0xee76b33b"
                }, 
                "2": {
                    "location": "RDX", 
                    "size": "0x8", 
                    "value": "0x309d0e9f"
                }, 
                "3": {
                    "location": "mem_0xe275d92226ec0644", 
                    "size": "0x8", 
                    "value": "0x3f280a531e2a1590"
                }, 
                "4": {
                    "location": "mem_0x2e605deaee76b33b", 
                    "size": "0x8", 
                    "value": "0x309d0e9f"
                }
            }
        }, 
        "3": {
            "inputs": {
                "0": {
                    "location": "RBP", 
                    "size": "0x8", 
                    "value": "0x8f5bbb7b466d739d"
                }, 
                "1": {
                    "location": "mem_0x0", 
                    "size": "0x8", 
                    "value": "0xb14ce243e099a9af"
                }, 
                "2": {
                    "location": "mem_0x1", 
                    "size": "0x8", 
                    "value": "0xe9f08cd64336cfd7"
                }, 
                "3": {
                    "location": "mem_0x2", 
                    "size": "0x4", 
                    "value": "0x57d22510"
                }
            }, 
            "outputs": {
                "0": {
                    "location": "RAX", 
                    "size": "0x8", 
                    "value": "0xe9f08cd64336cfd7"
                }, 
                "1": {
                    "location": "EAX", 
                    "size": "0x4", 
                    "value": "0x4336cfd7"
                }, 
                "2": {
                    "location": "RDX", 
                    "size": "0x8", 
                    "value": "0x57d22510"
                }, 
                "3": {
                    "location": "mem_0x8f5bbb7b466d65dd", 
                    "size": "0x8", 
                    "value": "0xb14ce243e099a9b0"
                }, 
                "4": {
                    "location": "mem_0xe9f08cd64336cfd7", 
                    "size": "0x8", 
                    "value": "0x57d22510"
                }
            }
        }, 
        "4": {
            "inputs": {
                "0": {
                    "location": "RBP", 
                    "size": "0x8", 
                    "value": "0xc2f8f8d642f7964b"
                }, 
                "1": {
                    "location": "mem_0x0", 
                    "size": "0x8", 
                    "value": "0xa6bdff308410ed70"
                }, 
                "2": {
                    "location": "mem_0x1", 
                    "size": "0x8", 
                    "value": "0x520c27431a44a34"
                }, 
                "3": {
                    "location": "mem_0x2", 
                    "size": "0x4", 
                    "value": "0xe384bc13"
                }
            }, 
            "outputs": {
                "0": {
                    "location": "RAX", 
                    "size": "0x8", 
                    "value": "0x520c27431a44a34"
                }, 
                "1": {
                    "location": "EAX", 
                    "size": "0x4", 
                    "value": "0x31a44a34"
                }, 
                "2": {
                    "location": "RDX", 
                    "size": "0x8", 
                    "value": "0xffffffffe384bc13"
                }, 
                "3": {
                    "location": "mem_0xc2f8f8d642f7888b", 
                    "size": "0x8", 
                    "value": "0xa6bdff308410ed71"
                }, 
                "4": {
                    "location": "mem_0x520c27431a44a34", 
                    "size": "0x8", 
                    "value": "0xffffffffe384bc13"
                }
            }
        }, 
        "5": {
            "inputs": {
                "0": {
                    "location": "RBP", 
                    "size": "0x8", 
                    "value": "0xe790371a8ab0e25f"
                }, 
                "1": {
                    "location": "mem_0x0", 
                    "size": "0x8", 
                    "value": "0x340906066ca5218d"
                }, 
                "2": {
                    "location": "mem_0x1", 
                    "size": "0x8", 
                    "value": "0xa45109ea3749e30d"
                }, 
                "3": {
                    "location": "mem_0x2", 
                    "size": "0x4", 
                    "value": "0x7a17bd5c"
                }
            }, 
            "outputs": {
                "0": {
                    "location": "RAX", 
                    "size": "0x8", 
                    "value": "0xa45109ea3749e30d"
                }, 
                "1": {
                    "location": "EAX", 
                    "size": "0x4", 
                    "value": "0x3749e30d"
                }, 
                "2": {
                    "location": "RDX", 
                    "size": "0x8", 
                    "value": "0x7a17bd5c"
                }, 
                "3": {
                    "location": "mem_0xe790371a8ab0d49f", 
                    "size": "0x8", 
                    "value": "0x340906066ca5218e"
                }, 
                "4": {
                    "location": "mem_0xa45109ea3749e30d", 
                    "size": "0x8", 
                    "value": "0x7a17bd5c"
                }
            }
        }, 
        "6": {
            "inputs": {
                "0": {
                    "location": "RBP", 
                    "size": "0x8", 
                    "value": "0x109fbe40d176b1a7"
                }, 
                "1": {
                    "location": "mem_0x0", 
                    "size": "0x8", 
                    "value": "0x51fc56493bdc3f"
                }, 
                "2": {
                    "location": "mem_0x1", 
                    "size": "0x8", 
                    "value": "0xb586c63891d008ff"
                }, 
                "3": {
                    "location": "mem_0x2", 
                    "size": "0x4", 
                    "value": "0xb7f37b2"
                }
            }, 
            "outputs": {
                "0": {
                    "location": "RAX", 
                    "size": "0x8", 
                    "value": "0xb586c63891d008ff"
                }, 
                "1": {
                    "location": "EAX", 
                    "size": "0x4", 
                    "value": "0x91d008ff"
                }, 
                "2": {
                    "location": "RDX", 
                    "size": "0x8", 
                    "value": "0xb7f37b2"
                }, 
                "3": {
                    "location": "mem_0x109fbe40d176a3e7", 
                    "size": "0x8", 
                    "value": "0x51fc56493bdc40"
                }, 
                "4": {
                    "location": "mem_0xb586c63891d008ff", 
                    "size": "0x8", 
                    "value": "0xb7f37b2"
                }
            }
        }, 
        "7": {
            "inputs": {
                "0": {
                    "location": "RBP", 
                    "size": "0x8", 
                    "value": "0x40c263e0fb10e9e7"
                }, 
                "1": {
                    "location": "mem_0x0", 
                    "size": "0x8", 
                    "value": "0xc46cf34e096b3aa3"
                }, 
                "2": {
                    "location": "mem_0x1", 
                    "size": "0x8", 
                    "value": "0x69443fec99b60d9d"
                }, 
                "3": {
                    "location": "mem_0x2", 
                    "size": "0x4", 
                    "value": "0x49e04e26"
                }
            }, 
            "outputs": {
                "0": {
                    "location": "RAX", 
                    "size": "0x8", 
                    "value": "0x69443fec99b60d9d"
                }, 
                "1": {
                    "location": "EAX", 
                    "size": "0x4", 
                    "value": "0x99b60d9d"
                }, 
                "2": {
                    "location": "RDX", 
                    "size": "0x8", 
                    "value": "0x49e04e26"
                }, 
                "3": {
                    "location": "mem_0x40c263e0fb10dc27", 
                    "size": "0x8", 
                    "value": "0xc46cf34e096b3aa4"
                }, 
                "4": {
                    "location": "mem_0x69443fec99b60d9d", 
                    "size": "0x8", 
                    "value": "0x49e04e26"
                }
            }
        }, 
        "8": {
            "inputs": {
                "0": {
                    "location": "RBP", 
                    "size": "0x8", 
                    "value": "0x7b4b7306d2987bac"
                }, 
                "1": {
                    "location": "mem_0x0", 
                    "size": "0x8", 
                    "value": "0xe93e1387a4b13840"
                }, 
                "2": {
                    "location": "mem_0x1", 
                    "size": "0x8", 
                    "value": "0x7f86c8973f0e2d81"
                }, 
                "3": {
                    "location": "mem_0x2", 
                    "size": "0x4", 
                    "value": "0x7da5dd15"
                }
            }, 
            "outputs": {
                "0": {
                    "location": "RAX", 
                    "size": "0x8", 
                    "value": "0x7f86c8973f0e2d81"
                }, 
                "1": {
                    "location": "EAX", 
                    "size": "0x4", 
                    "value": "0x3f0e2d81"
                }, 
                "2": {
                    "location": "RDX", 
                    "size": "0x8", 
                    "value": "0x7da5dd15"
                }, 
                "3": {
                    "location": "mem_0x7b4b7306d2986dec", 
                    "size": "0x8", 
                    "value": "0xe93e1387a4b13841"
                }, 
                "4": {
                    "location": "mem_0x7f86c8973f0e2d81", 
                    "size": "0x8", 
                    "value": "0x7da5dd15"
                }
            }
        }, 
        "9": {
            "inputs": {
                "0": {
                    "location": "RBP", 
                    "size": "0x8", 
                    "value": "0xca89645cbf89d839"
                }, 
                "1": {
                    "location": "mem_0x0", 
                    "size": "0x8", 
                    "value": "0xdb9a8128d5562ac4"
                }, 
                "2": {
                    "location": "mem_0x1", 
                    "size": "0x8", 
                    "value": "0x1951c33ae262e9d3"
                }, 
                "3": {
                    "location": "mem_0x2", 
                    "size": "0x4", 
                    "value": "0xe5890f20"
                }
            }, 
            "outputs": {
                "0": {
                    "location": "RAX", 
                    "size": "0x8", 
                    "value": "0x1951c33ae262e9d3"
                }, 
                "1": {
                    "location": "EAX", 
                    "size": "0x4", 
                    "value": "0xe262e9d3"
                }, 
                "2": {
                    "location": "RDX", 
                    "size": "0x8", 
                    "value": "0xffffffffe5890f20"
                }, 
                "3": {
                    "location": "mem_0xca89645cbf89ca79", 
                    "size": "0x8", 
                    "value": "0xdb9a8128d5562ac5"
                }, 
                "4": {
                    "location": "mem_0x1951c33ae262e9d3", 
                    "size": "0x8", 
                    "value": "0xffffffffe5890f20"
                }
            }
        }, 
        "10": {
            "inputs": {
                "0": {
                    "location": "RBP", 
                    "size": "0x8", 
                    "value": "0xf4f208633e4dee3"
                }, 
                "1": {
                    "location": "mem_0x0", 
                    "size": "0x8", 
                    "value": "0x4daff47142a00ab3"
                }, 
                "2": {
                    "location": "mem_0x1", 
                    "size": "0x8", 
                    "value": "0xdeb829d7634b7749"
                }, 
                "3": {
                    "location": "mem_0x2", 
                    "size": "0x4", 
                    "value": "0xb8388f74"
                }
            }, 
            "outputs": {
                "0": {
                    "location": "RAX", 
                    "size": "0x8", 
                    "value": "0xdeb829d7634b7749"
                }, 
                "1": {
                    "location": "EAX", 
                    "size": "0x4", 
                    "value": "0x634b7749"
                }, 
                "2": {
                    "location": "RDX", 
                    "size": "0x8", 
                    "value": "0xffffffffb8388f74"
                }, 
                "3": {
                    "location": "mem_0xf4f208633e4d123", 
                    "size": "0x8", 
                    "value": "0x4daff47142a00ab4"
                }, 
                "4": {
                    "location": "mem_0xdeb829d7634b7749", 
                    "size": "0x8", 
                    "value": "0xffffffffb8388f74"
                }
            }
        }, 
        "11": {
            "inputs": {
                "0": {
                    "location": "RBP", 
                    "size": "0x8", 
                    "value": "0x983a33e8480b9260"
                }, 
                "1": {
                    "location": "mem_0x0", 
                    "size": "0x8", 
                    "value": "0x720436dc286ade41"
                }, 
                "2": {
                    "location": "mem_0x1", 
                    "size": "0x8", 
                    "value": "0x2b35e7d9f48b81b4"
                }, 
                "3": {
                    "location": "mem_0x2", 
                    "size": "0x4", 
                    "value": "0xc058f523"
                }
            }, 
            "outputs": {
                "0": {
                    "location": "RAX", 
                    "size": "0x8", 
                    "value": "0x2b35e7d9f48b81b4"
                }, 
                "1": {
                    "location": "EAX", 
                    "size": "0x4", 
                    "value": "0xf48b81b4"
                }, 
                "2": {
                    "location": "RDX", 
                    "size": "0x8", 
                    "value": "0xffffffffc058f523"
                }, 
                "3": {
                    "location": "mem_0x983a33e8480b84a0", 
                    "size": "0x8", 
                    "value": "0x720436dc286ade42"
                }, 
                "4": {
                    "location": "mem_0x2b35e7d9f48b81b4", 
                    "size": "0x8", 
                    "value": "0xffffffffc058f523"
                }
            }
        }, 
        "12": {
            "inputs": {
                "0": {
                    "location": "RBP", 
                    "size": "0x8", 
                    "value": "0x3a5b362b2c0ed35b"
                }, 
                "1": {
                    "location": "mem_0x0", 
                    "size": "0x8", 
                    "value": "0xf40d28c5ac39c7d5"
                }, 
                "2": {
                    "location": "mem_0x1", 
                    "size": "0x8", 
                    "value": "0x131b629f1e370363"
                }, 
                "3": {
                    "location": "mem_0x2", 
                    "size": "0x4", 
                    "value": "0xa0a194f5"
                }
            }, 
            "outputs": {
                "0": {
                    "location": "RAX", 
                    "size": "0x8", 
                    "value": "0x131b629f1e370363"
                }, 
                "1": {
                    "location": "EAX", 
                    "size": "0x4", 
                    "value": "0x1e370363"
                }, 
                "2": {
                    "location": "RDX", 
                    "size": "0x8", 
                    "value": "0xffffffffa0a194f5"
                }, 
                "3": {
                    "location": "mem_0x3a5b362b2c0ec59b", 
                    "size": "0x8", 
                    "value": "0xf40d28c5ac39c7d6"
                }, 
                "4": {
                    "location": "mem_0x131b629f1e370363", 
                    "size": "0x8", 
                    "value": "0xffffffffa0a194f5"
                }
            }
        }, 
        "13": {
            "inputs": {
                "0": {
                    "location": "RBP", 
                    "size": "0x8", 
                    "value": "0x93b39d6cc3221e22"
                }, 
                "1": {
                    "location": "mem_0x0", 
                    "size": "0x8", 
                    "value": "0x4c270b825d91c41c"
                }, 
                "2": {
                    "location": "mem_0x1", 
                    "size": "0x8", 
                    "value": "0xdd344526501ae31b"
                }, 
                "3": {
                    "location": "mem_0x2", 
                    "size": "0x4", 
                    "value": "0xbe451328"
                }
            }, 
            "outputs": {
                "0": {
                    "location": "RAX", 
                    "size": "0x8", 
                    "value": "0xdd344526501ae31b"
                }, 
                "1": {
                    "location": "EAX", 
                    "size": "0x4", 
                    "value": "0x501ae31b"
                }, 
                "2": {
                    "location": "RDX", 
                    "size": "0x8", 
                    "value": "0xffffffffbe451328"
                }, 
                "3": {
                    "location": "mem_0x93b39d6cc3221062", 
                    "size": "0x8", 
                    "value": "0x4c270b825d91c41d"
                }, 
                "4": {
                    "location": "mem_0xdd344526501ae31b", 
                    "size": "0x8", 
                    "value": "0xffffffffbe451328"
                }
            }
        }, 
        "14": {
            "inputs": {
                "0": {
                    "location": "RBP", 
                    "size": "0x8", 
                    "value": "0x1ede64189cfc38bf"
                }, 
                "1": {
                    "location": "mem_0x0", 
                    "size": "0x8", 
                    "value": "0x241a9dbfb99538d7"
                }, 
                "2": {
                    "location": "mem_0x1", 
                    "size": "0x8", 
                    "value": "0xb545be30c2ba0590"
                }, 
                "3": {
                    "location": "mem_0x2", 
                    "size": "0x4", 
                    "value": "0xeb605b4"
                }
            }, 
            "outputs": {
                "0": {
                    "location": "RAX", 
                    "size": "0x8", 
                    "value": "0xb545be30c2ba0590"
                }, 
                "1": {
                    "location": "EAX", 
                    "size": "0x4", 
                    "value": "0xc2ba0590"
                }, 
                "2": {
                    "location": "RDX", 
                    "size": "0x8", 
                    "value": "0xeb605b4"
                }, 
                "3": {
                    "location": "mem_0x1ede64189cfc2aff", 
                    "size": "0x8", 
                    "value": "0x241a9dbfb99538d8"
                }, 
                "4": {
                    "location": "mem_0xb545be30c2ba0590", 
                    "size": "0x8", 
                    "value": "0xeb605b4"
                }
            }
        }, 
        "15": {
            "inputs": {
                "0": {
                    "location": "RBP", 
                    "size": "0x8", 
                    "value": "0xa3e72cfc366b7e2d"
                }, 
                "1": {
                    "location": "mem_0x0", 
                    "size": "0x8", 
                    "value": "0x67ed8c8f7f9b2fd1"
                }, 
                "2": {
                    "location": "mem_0x1", 
                    "size": "0x8", 
                    "value": "0x70230d18e2dd3b74"
                }, 
                "3": {
                    "location": "mem_0x2", 
                    "size": "0x4", 
                    "value": "0x98370898"
                }
            }, 
            "outputs": {
                "0": {
                    "location": "RAX", 
                    "size": "0x8", 
                    "value": "0x70230d18e2dd3b74"
                }, 
                "1": {
                    "location": "EAX", 
                    "size": "0x4", 
                    "value": "0xe2dd3b74"
                }, 
                "2": {
                    "location": "RDX", 
                    "size": "0x8", 
                    "value": "0xffffffff98370898"
                }, 
                "3": {
                    "location": "mem_0xa3e72cfc366b706d", 
                    "size": "0x8", 
                    "value": "0x67ed8c8f7f9b2fd2"
                }, 
                "4": {
                    "location": "mem_0x70230d18e2dd3b74", 
                    "size": "0x8", 
                    "value": "0xffffffff98370898"
                }
            }
        }, 
        "16": {
            "inputs": {
                "0": {
                    "location": "RBP", 
                    "size": "0x8", 
                    "value": "0x97220c1db2a6a1e5"
                }, 
                "1": {
                    "location": "mem_0x0", 
                    "size": "0x8", 
                    "value": "0x7ec0333f840cec71"
                }, 
                "2": {
                    "location": "mem_0x1", 
                    "size": "0x8", 
                    "value": "0x92b17193af6aa6bd"
                }, 
                "3": {
                    "location": "mem_0x2", 
                    "size": "0x4", 
                    "value": "0x3c16978a"
                }
            }, 
            "outputs": {
                "0": {
                    "location": "RAX", 
                    "size": "0x8", 
                    "value": "0x92b17193af6aa6bd"
                }, 
                "1": {
                    "location": "EAX", 
                    "size": "0x4", 
                    "value": "0xaf6aa6bd"
                }, 
                "2": {
                    "location": "RDX", 
                    "size": "0x8", 
                    "value": "0x3c16978a"
                }, 
                "3": {
                    "location": "mem_0x97220c1db2a69425", 
                    "size": "0x8", 
                    "value": "0x7ec0333f840cec72"
                }, 
                "4": {
                    "location": "mem_0x92b17193af6aa6bd", 
                    "size": "0x8", 
                    "value": "0x3c16978a"
                }
            }
        }, 
        "17": {
            "inputs": {
                "0": {
                    "location": "RBP", 
                    "size": "0x8", 
                    "value": "0x44bb9ec5a51bad6b"
                }, 
                "1": {
                    "location": "mem_0x0", 
                    "size": "0x8", 
                    "value": "0xb5b6559cbe7d80ba"
                }, 
                "2": {
                    "location": "mem_0x1", 
                    "size": "0x8", 
                    "value": "0xd1d295d042ee2ce3"
                }, 
                "3": {
                    "location": "mem_0x2", 
                    "size": "0x4", 
                    "value": "0xf4c265e9"
                }
            }, 
            "outputs": {
                "0": {
                    "location": "RAX", 
                    "size": "0x8", 
                    "value": "0xd1d295d042ee2ce3"
                }, 
                "1": {
                    "location": "EAX", 
                    "size": "0x4", 
                    "value": "0x42ee2ce3"
                }, 
                "2": {
                    "location": "RDX", 
                    "size": "0x8", 
                    "value": "0xfffffffff4c265e9"
                }, 
                "3": {
                    "location": "mem_0x44bb9ec5a51b9fab", 
                    "size": "0x8", 
                    "value": "0xb5b6559cbe7d80bb"
                }, 
                "4": {
                    "location": "mem_0xd1d295d042ee2ce3", 
                    "size": "0x8", 
                    "value": "0xfffffffff4c265e9"
                }
            }
        }, 
        "18": {
            "inputs": {
                "0": {
                    "location": "RBP", 
                    "size": "0x8", 
                    "value": "0x18700b08c6959bd2"
                }, 
                "1": {
                    "location": "mem_0x0", 
                    "size": "0x8", 
                    "value": "0x8107fb1760db2a22"
                }, 
                "2": {
                    "location": "mem_0x1", 
                    "size": "0x8", 
                    "value": "0xe8e1322bf2d0728a"
                }, 
                "3": {
                    "location": "mem_0x2", 
                    "size": "0x4", 
                    "value": "0xc9dc569a"
                }
            }, 
            "outputs": {
                "0": {
                    "location": "RAX", 
                    "size": "0x8", 
                    "value": "0xe8e1322bf2d0728a"
                }, 
                "1": {
                    "location": "EAX", 
                    "size": "0x4", 
                    "value": "0xf2d0728a"
                }, 
                "2": {
                    "location": "RDX", 
                    "size": "0x8", 
                    "value": "0xffffffffc9dc569a"
                }, 
                "3": {
                    "location": "mem_0x18700b08c6958e12", 
                    "size": "0x8", 
                    "value": "0x8107fb1760db2a23"
                }, 
                "4": {
                    "location": "mem_0xe8e1322bf2d0728a", 
                    "size": "0x8", 
                    "value": "0xffffffffc9dc569a"
                }
            }
        }, 
        "19": {
            "inputs": {
                "0": {
                    "location": "RBP", 
                    "size": "0x8", 
                    "value": "0xbfff1bbf53bb9671"
                }, 
                "1": {
                    "location": "mem_0x0", 
                    "size": "0x8", 
                    "value": "0x7e9c35e113e9772c"
                }, 
                "2": {
                    "location": "mem_0x1", 
                    "size": "0x8", 
                    "value": "0xf85d431a5af12a3d"
                }, 
                "3": {
                    "location": "mem_0x2", 
                    "size": "0x4", 
                    "value": "0xb44f74db"
                }
            }, 
            "outputs": {
                "0": {
                    "location": "RAX", 
                    "size": "0x8", 
                    "value": "0xf85d431a5af12a3d"
                }, 
                "1": {
                    "location": "EAX", 
                    "size": "0x4", 
                    "value": "0x5af12a3d"
                }, 
                "2": {
                    "location": "RDX", 
                    "size": "0x8", 
                    "value": "0xffffffffb44f74db"
                }, 
                "3": {
                    "location": "mem_0xbfff1bbf53bb88b1", 
                    "size": "0x8", 
                    "value": "0x7e9c35e113e9772d"
                }, 
                "4": {
                    "location": "mem_0xf85d431a5af12a3d", 
                    "size": "0x8", 
                    "value": "0xffffffffb44f74db"
                }
            }
        }, 
        "20": {
            "inputs": {
                "0": {
                    "location": "RBP", 
                    "size": "0x8", 
                    "value": "0x40ec1b15ea2fd2ef"
                }, 
                "1": {
                    "location": "mem_0x0", 
                    "size": "0x8", 
                    "value": "0x5d12080c4aa210a"
                }, 
                "2": {
                    "location": "mem_0x1", 
                    "size": "0x8", 
                    "value": "0x6709fc4b310c4a76"
                }, 
                "3": {
                    "location": "mem_0x2", 
                    "size": "0x4", 
                    "value": "0x6033aa1c"
                }
            }, 
            "outputs": {
                "0": {
                    "location": "RAX", 
                    "size": "0x8", 
                    "value": "0x6709fc4b310c4a76"
                }, 
                "1": {
                    "location": "EAX", 
                    "size": "0x4", 
                    "value": "0x310c4a76"
                }, 
                "2": {
                    "location": "RDX", 
                    "size": "0x8", 
                    "value": "0x6033aa1c"
                }, 
                "3": {
                    "location": "mem_0x40ec1b15ea2fc52f", 
                    "size": "0x8", 
                    "value": "0x5d12080c4aa210b"
                }, 
                "4": {
                    "location": "mem_0x6709fc4b310c4a76", 
                    "size": "0x8", 
                    "value": "0x6033aa1c"
                }
            }
        }, 
        "21": {
            "inputs": {
                "0": {
                    "location": "RBP", 
                    "size": "0x8", 
                    "value": "0x8f006bd241ae96c9"
                }, 
                "1": {
                    "location": "mem_0x0", 
                    "size": "0x8", 
                    "value": "0xfa900bea1890d6a"
                }, 
                "2": {
                    "location": "mem_0x1", 
                    "size": "0x8", 
                    "value": "0x53a9cf19fc9ad63c"
                }, 
                "3": {
                    "location": "mem_0x2", 
                    "size": "0x4", 
                    "value": "0x573572d6"
                }
            }, 
            "outputs": {
                "0": {
                    "location": "RAX", 
                    "size": "0x8", 
                    "value": "0x53a9cf19fc9ad63c"
                }, 
                "1": {
                    "location": "EAX", 
                    "size": "0x4", 
                    "value": "0xfc9ad63c"
                }, 
                "2": {
                    "location": "RDX", 
                    "size": "0x8", 
                    "value": "0x573572d6"
                }, 
                "3": {
                    "location": "mem_0x8f006bd241ae8909", 
                    "size": "0x8", 
                    "value": "0xfa900bea1890d6b"
                }, 
                "4": {
                    "location": "mem_0x53a9cf19fc9ad63c", 
                    "size": "0x8", 
                    "value": "0x573572d6"
                }
            }
        }, 
        "22": {
            "inputs": {
                "0": {
                    "location": "RBP", 
                    "size": "0x8", 
                    "value": "0x5166fbe613cfd97f"
                }, 
                "1": {
                    "location": "mem_0x0", 
                    "size": "0x8", 
                    "value": "0xba172178e5505343"
                }, 
                "2": {
                    "location": "mem_0x1", 
                    "size": "0x8", 
                    "value": "0xada332577243140f"
                }, 
                "3": {
                    "location": "mem_0x2", 
                    "size": "0x4", 
                    "value": "0xe05d6b29"
                }
            }, 
            "outputs": {
                "0": {
                    "location": "RAX", 
                    "size": "0x8", 
                    "value": "0xada332577243140f"
                }, 
                "1": {
                    "location": "EAX", 
                    "size": "0x4", 
                    "value": "0x7243140f"
                }, 
                "2": {
                    "location": "RDX", 
                    "size": "0x8", 
                    "value": "0xffffffffe05d6b29"
                }, 
                "3": {
                    "location": "mem_0x5166fbe613cfcbbf", 
                    "size": "0x8", 
                    "value": "0xba172178e5505344"
                }, 
                "4": {
                    "location": "mem_0xada332577243140f", 
                    "size": "0x8", 
                    "value": "0xffffffffe05d6b29"
                }
            }
        }, 
        "23": {
            "inputs": {
                "0": {
                    "location": "RBP", 
                    "size": "0x8", 
                    "value": "0x4b616e91e29df566"
                }, 
                "1": {
                    "location": "mem_0x0", 
                    "size": "0x8", 
                    "value": "0x35492e00087d1e25"
                }, 
                "2": {
                    "location": "mem_0x1", 
                    "size": "0x8", 
                    "value": "0xfa6474d78eef6f70"
                }, 
                "3": {
                    "location": "mem_0x2", 
                    "size": "0x4", 
                    "value": "0xad1e921e"
                }
            }, 
            "outputs": {
                "0": {
                    "location": "RAX", 
                    "size": "0x8", 
                    "value": "0xfa6474d78eef6f70"
                }, 
                "1": {
                    "location": "EAX", 
                    "size": "0x4", 
                    "value": "0x8eef6f70"
                }, 
                "2": {
                    "location": "RDX", 
                    "size": "0x8", 
                    "value": "0xffffffffad1e921e"
                }, 
                "3": {
                    "location": "mem_0x4b616e91e29de7a6", 
                    "size": "0x8", 
                    "value": "0x35492e00087d1e26"
                }, 
                "4": {
                    "location": "mem_0xfa6474d78eef6f70", 
                    "size": "0x8", 
                    "value": "0xffffffffad1e921e"
                }
            }
        }, 
        "24": {
            "inputs": {
                "0": {
                    "location": "RBP", 
                    "size": "0x8", 
                    "value": "0xb685c42577fb2e12"
                }, 
                "1": {
                    "location": "mem_0x0", 
                    "size": "0x8", 
                    "value": "0xb76e017f8b483d77"
                }, 
                "2": {
                    "location": "mem_0x1", 
                    "size": "0x8", 
                    "value": "0x4cc41bb0d4b0bc6"
                }, 
                "3": {
                    "location": "mem_0x2", 
                    "size": "0x4", 
                    "value": "0xf681b057"
                }
            }, 
            "outputs": {
                "0": {
                    "location": "RAX", 
                    "size": "0x8", 
                    "value": "0x4cc41bb0d4b0bc6"
                }, 
                "1": {
                    "location": "EAX", 
                    "size": "0x4", 
                    "value": "0xd4b0bc6"
                }, 
                "2": {
                    "location": "RDX", 
                    "size": "0x8", 
                    "value": "0xfffffffff681b057"
                }, 
                "3": {
                    "location": "mem_0xb685c42577fb2052", 
                    "size": "0x8", 
                    "value": "0xb76e017f8b483d78"
                }, 
                "4": {
                    "location": "mem_0x4cc41bb0d4b0bc6", 
                    "size": "0x8", 
                    "value": "0xfffffffff681b057"
                }
            }
        }, 
        "25": {
            "inputs": {
                "0": {
                    "location": "RBP", 
                    "size": "0x8", 
                    "value": "0x58b856c2fe777707"
                }, 
                "1": {
                    "location": "mem_0x0", 
                    "size": "0x8", 
                    "value": "0x6d3d095609b722a1"
                }, 
                "2": {
                    "location": "mem_0x1", 
                    "size": "0x8", 
                    "value": "0xbea81c5b001ca9"
                }, 
                "3": {
                    "location": "mem_0x2", 
                    "size": "0x4", 
                    "value": "0x5e9890b8"
                }
            }, 
            "outputs": {
                "0": {
                    "location": "RAX", 
                    "size": "0x8", 
                    "value": "0xbea81c5b001ca9"
                }, 
                "1": {
                    "location": "EAX", 
                    "size": "0x4", 
                    "value": "0x5b001ca9"
                }, 
                "2": {
                    "location": "RDX", 
                    "size": "0x8", 
                    "value": "0x5e9890b8"
                }, 
                "3": {
                    "location": "mem_0x58b856c2fe776947", 
                    "size": "0x8", 
                    "value": "0x6d3d095609b722a2"
                }, 
                "4": {
                    "location": "mem_0xbea81c5b001ca9", 
                    "size": "0x8", 
                    "value": "0x5e9890b8"
                }
            }
        }, 
        "26": {
            "inputs": {
                "0": {
                    "location": "RBP", 
                    "size": "0x8", 
                    "value": "0x4220f203eb97473f"
                }, 
                "1": {
                    "location": "mem_0x0", 
                    "size": "0x8", 
                    "value": "0x13d6decb32df8546"
                }, 
                "2": {
                    "location": "mem_0x1", 
                    "size": "0x8", 
                    "value": "0x7f119e7995966a2f"
                }, 
                "3": {
                    "location": "mem_0x2", 
                    "size": "0x4", 
                    "value": "0x45b38732"
                }
            }, 
            "outputs": {
                "0": {
                    "location": "RAX", 
                    "size": "0x8", 
                    "value": "0x7f119e7995966a2f"
                }, 
                "1": {
                    "location": "EAX", 
                    "size": "0x4", 
                    "value": "0x95966a2f"
                }, 
                "2": {
                    "location": "RDX", 
                    "size": "0x8", 
                    "value": "0x45b38732"
                }, 
                "3": {
                    "location": "mem_0x4220f203eb97397f", 
                    "size": "0x8", 
                    "value": "0x13d6decb32df8547"
                }, 
                "4": {
                    "location": "mem_0x7f119e7995966a2f", 
                    "size": "0x8", 
                    "value": "0x45b38732"
                }
            }
        }, 
        "27": {
            "inputs": {
                "0": {
                    "location": "RBP", 
                    "size": "0x8", 
                    "value": "0xbdc861c33824805"
                }, 
                "1": {
                    "location": "mem_0x0", 
                    "size": "0x8", 
                    "value": "0xc78601511fa65bcd"
                }, 
                "2": {
                    "location": "mem_0x1", 
                    "size": "0x8", 
                    "value": "0xf78514521ccd7255"
                }, 
                "3": {
                    "location": "mem_0x2", 
                    "size": "0x4", 
                    "value": "0x3403e277"
                }
            }, 
            "outputs": {
                "0": {
                    "location": "RAX", 
                    "size": "0x8", 
                    "value": "0xf78514521ccd7255"
                }, 
                "1": {
                    "location": "EAX", 
                    "size": "0x4", 
                    "value": "0x1ccd7255"
                }, 
                "2": {
                    "location": "RDX", 
                    "size": "0x8", 
                    "value": "0x3403e277"
                }, 
                "3": {
                    "location": "mem_0xbdc861c33823a45", 
                    "size": "0x8", 
                    "value": "0xc78601511fa65bce"
                }, 
                "4": {
                    "location": "mem_0xf78514521ccd7255", 
                    "size": "0x8", 
                    "value": "0x3403e277"
                }
            }
        }, 
        "28": {
            "inputs": {
                "0": {
                    "location": "RBP", 
                    "size": "0x8", 
                    "value": "0xb40d85614745237"
                }, 
                "1": {
                    "location": "mem_0x0", 
                    "size": "0x8", 
                    "value": "0xf8e609502bbb199b"
                }, 
                "2": {
                    "location": "mem_0x1", 
                    "size": "0x8", 
                    "value": "0x68a64e82aaa7f867"
                }, 
                "3": {
                    "location": "mem_0x2", 
                    "size": "0x4", 
                    "value": "0x80169196"
                }
            }, 
            "outputs": {
                "0": {
                    "location": "RAX", 
                    "size": "0x8", 
                    "value": "0x68a64e82aaa7f867"
                }, 
                "1": {
                    "location": "EAX", 
                    "size": "0x4", 
                    "value": "0xaaa7f867"
                }, 
                "2": {
                    "location": "RDX", 
                    "size": "0x8", 
                    "value": "0xffffffff80169196"
                }, 
                "3": {
                    "location": "mem_0xb40d85614744477", 
                    "size": "0x8", 
                    "value": "0xf8e609502bbb199c"
                }, 
                "4": {
                    "location": "mem_0x68a64e82aaa7f867", 
                    "size": "0x8", 
                    "value": "0xffffffff80169196"
                }
            }
        }, 
        "29": {
            "inputs": {
                "0": {
                    "location": "RBP", 
                    "size": "0x8", 
                    "value": "0xa41fee77ba3fdff"
                }, 
                "1": {
                    "location": "mem_0x0", 
                    "size": "0x8", 
                    "value": "0x4bc17579637b7ab4"
                }, 
                "2": {
                    "location": "mem_0x1", 
                    "size": "0x8", 
                    "value": "0xc0bfc68387277c5f"
                }, 
                "3": {
                    "location": "mem_0x2", 
                    "size": "0x4", 
                    "value": "0x7269869c"
                }
            }, 
            "outputs": {
                "0": {
                    "location": "RAX", 
                    "size": "0x8", 
                    "value": "0xc0bfc68387277c5f"
                }, 
                "1": {
                    "location": "EAX", 
                    "size": "0x4", 
                    "value": "0x87277c5f"
                }, 
                "2": {
                    "location": "RDX", 
                    "size": "0x8", 
                    "value": "0x7269869c"
                }, 
                "3": {
                    "location": "mem_0xa41fee77ba3f03f", 
                    "size": "0x8", 
                    "value": "0x4bc17579637b7ab5"
                }, 
                "4": {
                    "location": "mem_0xc0bfc68387277c5f", 
                    "size": "0x8", 
                    "value": "0x7269869c"
                }
            }
        }, 
        "30": {
            "inputs": {
                "0": {
                    "location": "RBP", 
                    "size": "0x8", 
                    "value": "0x2cb04f09b04840d2"
                }, 
                "1": {
                    "location": "mem_0x0", 
                    "size": "0x8", 
                    "value": "0x5680ab4771ee37e7"
                }, 
                "2": {
                    "location": "mem_0x1", 
                    "size": "0x8", 
                    "value": "0xe8a572ee6a41a89e"
                }, 
                "3": {
                    "location": "mem_0x2", 
                    "size": "0x4", 
                    "value": "0xb049d87a"
                }
            }, 
            "outputs": {
                "0": {
                    "location": "RAX", 
                    "size": "0x8", 
                    "value": "0xe8a572ee6a41a89e"
                }, 
                "1": {
                    "location": "EAX", 
                    "size": "0x4", 
                    "value": "0x6a41a89e"
                }, 
                "2": {
                    "location": "RDX", 
                    "size": "0x8", 
                    "value": "0xffffffffb049d87a"
                }, 
                "3": {
                    "location": "mem_0x2cb04f09b0483312", 
                    "size": "0x8", 
                    "value": "0x5680ab4771ee37e8"
                }, 
                "4": {
                    "location": "mem_0xe8a572ee6a41a89e", 
                    "size": "0x8", 
                    "value": "0xffffffffb049d87a"
                }
            }
        }, 
        "31": {
            "inputs": {
                "0": {
                    "location": "RBP", 
                    "size": "0x8", 
                    "value": "0x2fcb7a2b9bccc034"
                }, 
                "1": {
                    "location": "mem_0x0", 
                    "size": "0x8", 
                    "value": "0x5f4a78c3134e7f1f"
                }, 
                "2": {
                    "location": "mem_0x1", 
                    "size": "0x8", 
                    "value": "0x26c1f02a2abb7d54"
                }, 
                "3": {
                    "location": "mem_0x2", 
                    "size": "0x4", 
                    "value": "0x919bb234"
                }
            }, 
            "outputs": {
                "0": {
                    "location": "RAX", 
                    "size": "0x8", 
                    "value": "0x26c1f02a2abb7d54"
                }, 
                "1": {
                    "location": "EAX", 
                    "size": "0x4", 
                    "value": "0x2abb7d54"
                }, 
                "2": {
                    "location": "RDX", 
                    "size": "0x8", 
                    "value": "0xffffffff919bb234"
                }, 
                "3": {
                    "location": "mem_0x2fcb7a2b9bccb274", 
                    "size": "0x8", 
                    "value": "0x5f4a78c3134e7f20"
                }, 
                "4": {
                    "location": "mem_0x26c1f02a2abb7d54", 
                    "size": "0x8", 
                    "value": "0xffffffff919bb234"
                }
            }
        }, 
        "32": {
            "inputs": {
                "0": {
                    "location": "RBP", 
                    "size": "0x8", 
                    "value": "0x27f7bb75dccf514a"
                }, 
                "1": {
                    "location": "mem_0x0", 
                    "size": "0x8", 
                    "value": "0x514518287c53106f"
                }, 
                "2": {
                    "location": "mem_0x1", 
                    "size": "0x8", 
                    "value": "0x8ff20d6207492062"
                }, 
                "3": {
                    "location": "mem_0x2", 
                    "size": "0x4", 
                    "value": "0xcea73408"
                }
            }, 
            "outputs": {
                "0": {
                    "location": "RAX", 
                    "size": "0x8", 
                    "value": "0x8ff20d6207492062"
                }, 
                "1": {
                    "location": "EAX", 
                    "size": "0x4", 
                    "value": "0x7492062"
                }, 
                "2": {
                    "location": "RDX", 
                    "size": "0x8", 
                    "value": "0xffffffffcea73408"
                }, 
                "3": {
                    "location": "mem_0x27f7bb75dccf438a", 
                    "size": "0x8", 
                    "value": "0x514518287c531070"
                }, 
                "4": {
                    "location": "mem_0x8ff20d6207492062", 
                    "size": "0x8", 
                    "value": "0xffffffffcea73408"
                }
            }
        }, 
        "33": {
            "inputs": {
                "0": {
                    "location": "RBP", 
                    "size": "0x8", 
                    "value": "0xa5d6f68cdff2d349"
                }, 
                "1": {
                    "location": "mem_0x0", 
                    "size": "0x8", 
                    "value": "0xc2805dc67c5f161e"
                }, 
                "2": {
                    "location": "mem_0x1", 
                    "size": "0x8", 
                    "value": "0xb03676fdd0a68820"
                }, 
                "3": {
                    "location": "mem_0x2", 
                    "size": "0x4", 
                    "value": "0x44d8917a"
                }
            }, 
            "outputs": {
                "0": {
                    "location": "RAX", 
                    "size": "0x8", 
                    "value": "0xb03676fdd0a68820"
                }, 
                "1": {
                    "location": "EAX", 
                    "size": "0x4", 
                    "value": "0xd0a68820"
                }, 
                "2": {
                    "location": "RDX", 
                    "size": "0x8", 
                    "value": "0x44d8917a"
                }, 
                "3": {
                    "location": "mem_0xa5d6f68cdff2c589", 
                    "size": "0x8", 
                    "value": "0xc2805dc67c5f161f"
                }, 
                "4": {
                    "location": "mem_0xb03676fdd0a68820", 
                    "size": "0x8", 
                    "value": "0x44d8917a"
                }
            }
        }, 
        "34": {
            "inputs": {
                "0": {
                    "location": "RBP", 
                    "size": "0x8", 
                    "value": "0x56524cd30973e749"
                }, 
                "1": {
                    "location": "mem_0x0", 
                    "size": "0x8", 
                    "value": "0xabf714f6adf86a5c"
                }, 
                "2": {
                    "location": "mem_0x1", 
                    "size": "0x8", 
                    "value": "0xae425de159bb93d7"
                }, 
                "3": {
                    "location": "mem_0x2", 
                    "size": "0x4", 
                    "value": "0x1af5278f"
                }
            }, 
            "outputs": {
                "0": {
                    "location": "RAX", 
                    "size": "0x8", 
                    "value": "0xae425de159bb93d7"
                }, 
                "1": {
                    "location": "EAX", 
                    "size": "0x4", 
                    "value": "0x59bb93d7"
                }, 
                "2": {
                    "location": "RDX", 
                    "size": "0x8", 
                    "value": "0x1af5278f"
                }, 
                "3": {
                    "location": "mem_0x56524cd30973d989", 
                    "size": "0x8", 
                    "value": "0xabf714f6adf86a5d"
                }, 
                "4": {
                    "location": "mem_0xae425de159bb93d7", 
                    "size": "0x8", 
                    "value": "0x1af5278f"
                }
            }
        }, 
        "35": {
            "inputs": {
                "0": {
                    "location": "RBP", 
                    "size": "0x8", 
                    "value": "0x5e10f4953f4ac36b"
                }, 
                "1": {
                    "location": "mem_0x0", 
                    "size": "0x8", 
                    "value": "0x2e5b7fe1e5f60d6e"
                }, 
                "2": {
                    "location": "mem_0x1", 
                    "size": "0x8", 
                    "value": "0xb721c477020a7b03"
                }, 
                "3": {
                    "location": "mem_0x2", 
                    "size": "0x4", 
                    "value": "0x9e5e6510"
                }
            }, 
            "outputs": {
                "0": {
                    "location": "RAX", 
                    "size": "0x8", 
                    "value": "0xb721c477020a7b03"
                }, 
                "1": {
                    "location": "EAX", 
                    "size": "0x4", 
                    "value": "0x20a7b03"
                }, 
                "2": {
                    "location": "RDX", 
                    "size": "0x8", 
                    "value": "0xffffffff9e5e6510"
                }, 
                "3": {
                    "location": "mem_0x5e10f4953f4ab5ab", 
                    "size": "0x8", 
                    "value": "0x2e5b7fe1e5f60d6f"
                }, 
                "4": {
                    "location": "mem_0xb721c477020a7b03", 
                    "size": "0x8", 
                    "value": "0xffffffff9e5e6510"
                }
            }
        }, 
        "36": {
            "inputs": {
                "0": {
                    "location": "RBP", 
                    "size": "0x8", 
                    "value": "0xae16ca1190f744be"
                }, 
                "1": {
                    "location": "mem_0x0", 
                    "size": "0x8", 
                    "value": "0x8e7f7e33f129cb81"
                }, 
                "2": {
                    "location": "mem_0x1", 
                    "size": "0x8", 
                    "value": "0x8903ab6c1c95141f"
                }, 
                "3": {
                    "location": "mem_0x2", 
                    "size": "0x4", 
                    "value": "0xc7406904"
                }
            }, 
            "outputs": {
                "0": {
                    "location": "RAX", 
                    "size": "0x8", 
                    "value": "0x8903ab6c1c95141f"
                }, 
                "1": {
                    "location": "EAX", 
                    "size": "0x4", 
                    "value": "0x1c95141f"
                }, 
                "2": {
                    "location": "RDX", 
                    "size": "0x8", 
                    "value": "0xffffffffc7406904"
                }, 
                "3": {
                    "location": "mem_0xae16ca1190f736fe", 
                    "size": "0x8", 
                    "value": "0x8e7f7e33f129cb82"
                }, 
                "4": {
                    "location": "mem_0x8903ab6c1c95141f", 
                    "size": "0x8", 
                    "value": "0xffffffffc7406904"
                }
            }
        }, 
        "37": {
            "inputs": {
                "0": {
                    "location": "RBP", 
                    "size": "0x8", 
                    "value": "0x4ff90a30b70fb86e"
                }, 
                "1": {
                    "location": "mem_0x0", 
                    "size": "0x8", 
                    "value": "0x92954ef86024f902"
                }, 
                "2": {
                    "location": "mem_0x1", 
                    "size": "0x8", 
                    "value": "0x3cb20fa4d2b689b4"
                }, 
                "3": {
                    "location": "mem_0x2", 
                    "size": "0x4", 
                    "value": "0x80ee1ad0"
                }
            }, 
            "outputs": {
                "0": {
                    "location": "RAX", 
                    "size": "0x8", 
                    "value": "0x3cb20fa4d2b689b4"
                }, 
                "1": {
                    "location": "EAX", 
                    "size": "0x4", 
                    "value": "0xd2b689b4"
                }, 
                "2": {
                    "location": "RDX", 
                    "size": "0x8", 
                    "value": "0xffffffff80ee1ad0"
                }, 
                "3": {
                    "location": "mem_0x4ff90a30b70faaae", 
                    "size": "0x8", 
                    "value": "0x92954ef86024f903"
                }, 
                "4": {
                    "location": "mem_0x3cb20fa4d2b689b4", 
                    "size": "0x8", 
                    "value": "0xffffffff80ee1ad0"
                }
            }
        }, 
        "38": {
            "inputs": {
                "0": {
                    "location": "RBP", 
                    "size": "0x8", 
                    "value": "0x7ce3fb4a673a0a64"
                }, 
                "1": {
                    "location": "mem_0x0", 
                    "size": "0x8", 
                    "value": "0x377714b1559ecb26"
                }, 
                "2": {
                    "location": "mem_0x1", 
                    "size": "0x8", 
                    "value": "0x3cad70a9a7c34308"
                }, 
                "3": {
                    "location": "mem_0x2", 
                    "size": "0x4", 
                    "value": "0xfa7b65e7"
                }
            }, 
            "outputs": {
                "0": {
                    "location": "RAX", 
                    "size": "0x8", 
                    "value": "0x3cad70a9a7c34308"
                }, 
                "1": {
                    "location": "EAX", 
                    "size": "0x4", 
                    "value": "0xa7c34308"
                }, 
                "2": {
                    "location": "RDX", 
                    "size": "0x8", 
                    "value": "0xfffffffffa7b65e7"
                }, 
                "3": {
                    "location": "mem_0x7ce3fb4a6739fca4", 
                    "size": "0x8", 
                    "value": "0x377714b1559ecb27"
                }, 
                "4": {
                    "location": "mem_0x3cad70a9a7c34308", 
                    "size": "0x8", 
                    "value": "0xfffffffffa7b65e7"
                }
            }
        }, 
        "39": {
            "inputs": {
                "0": {
                    "location": "RBP", 
                    "size": "0x8", 
                    "value": "0x221d2117ee540d40"
                }, 
                "1": {
                    "location": "mem_0x0", 
                    "size": "0x8", 
                    "value": "0x7d254f2f5c874770"
                }, 
                "2": {
                    "location": "mem_0x1", 
                    "size": "0x8", 
                    "value": "0xf9e1a0b57e33de39"
                }, 
                "3": {
                    "location": "mem_0x2", 
                    "size": "0x4", 
                    "value": "0x4e3b9e83"
                }
            }, 
            "outputs": {
                "0": {
                    "location": "RAX", 
                    "size": "0x8", 
                    "value": "0xf9e1a0b57e33de39"
                }, 
                "1": {
                    "location": "EAX", 
                    "size": "0x4", 
                    "value": "0x7e33de39"
                }, 
                "2": {
                    "location": "RDX", 
                    "size": "0x8", 
                    "value": "0x4e3b9e83"
                }, 
                "3": {
                    "location": "mem_0x221d2117ee53ff80", 
                    "size": "0x8", 
                    "value": "0x7d254f2f5c874771"
                }, 
                "4": {
                    "location": "mem_0xf9e1a0b57e33de39", 
                    "size": "0x8", 
                    "value": "0x4e3b9e83"
                }
            }
        }, 
        "40": {
            "inputs": {
                "0": {
                    "location": "RBP", 
                    "size": "0x8", 
                    "value": "0x9afeec45f963768d"
                }, 
                "1": {
                    "location": "mem_0x0", 
                    "size": "0x8", 
                    "value": "0x8c9c35410fb1b7a9"
                }, 
                "2": {
                    "location": "mem_0x1", 
                    "size": "0x8", 
                    "value": "0x782182bdb3a527ac"
                }, 
                "3": {
                    "location": "mem_0x2", 
                    "size": "0x4", 
                    "value": "0x714a3cd6"
                }
            }, 
            "outputs": {
                "0": {
                    "location": "RAX", 
                    "size": "0x8", 
                    "value": "0x782182bdb3a527ac"
                }, 
                "1": {
                    "location": "EAX", 
                    "size": "0x4", 
                    "value": "0xb3a527ac"
                }, 
                "2": {
                    "location": "RDX", 
                    "size": "0x8", 
                    "value": "0x714a3cd6"
                }, 
                "3": {
                    "location": "mem_0x9afeec45f96368cd", 
                    "size": "0x8", 
                    "value": "0x8c9c35410fb1b7aa"
                }, 
                "4": {
                    "location": "mem_0x782182bdb3a527ac", 
                    "size": "0x8", 
                    "value": "0x714a3cd6"
                }
            }
        }, 
        "41": {
            "inputs": {
                "0": {
                    "location": "RBP", 
                    "size": "0x8", 
                    "value": "0x1b4d745d002f1331"
                }, 
                "1": {
                    "location": "mem_0x0", 
                    "size": "0x8", 
                    "value": "0x1e3dd85e36e1dca3"
                }, 
                "2": {
                    "location": "mem_0x1", 
                    "size": "0x8", 
                    "value": "0xd828a5c75d0f431e"
                }, 
                "3": {
                    "location": "mem_0x2", 
                    "size": "0x4", 
                    "value": "0x26f0a87b"
                }
            }, 
            "outputs": {
                "0": {
                    "location": "RAX", 
                    "size": "0x8", 
                    "value": "0xd828a5c75d0f431e"
                }, 
                "1": {
                    "location": "EAX", 
                    "size": "0x4", 
                    "value": "0x5d0f431e"
                }, 
                "2": {
                    "location": "RDX", 
                    "size": "0x8", 
                    "value": "0x26f0a87b"
                }, 
                "3": {
                    "location": "mem_0x1b4d745d002f0571", 
                    "size": "0x8", 
                    "value": "0x1e3dd85e36e1dca4"
                }, 
                "4": {
                    "location": "mem_0xd828a5c75d0f431e", 
                    "size": "0x8", 
                    "value": "0x26f0a87b"
                }
            }
        }, 
        "42": {
            "inputs": {
                "0": {
                    "location": "RBP", 
                    "size": "0x8", 
                    "value": "0x938caf9b3400956b"
                }, 
                "1": {
                    "location": "mem_0x0", 
                    "size": "0x8", 
                    "value": "0xa9b6172ad4b1f5e7"
                }, 
                "2": {
                    "location": "mem_0x1", 
                    "size": "0x8", 
                    "value": "0x8ad627f17ab8abf3"
                }, 
                "3": {
                    "location": "mem_0x2", 
                    "size": "0x4", 
                    "value": "0xa53e8e56"
                }
            }, 
            "outputs": {
                "0": {
                    "location": "RAX", 
                    "size": "0x8", 
                    "value": "0x8ad627f17ab8abf3"
                }, 
                "1": {
                    "location": "EAX", 
                    "size": "0x4", 
                    "value": "0x7ab8abf3"
                }, 
                "2": {
                    "location": "RDX", 
                    "size": "0x8", 
                    "value": "0xffffffffa53e8e56"
                }, 
                "3": {
                    "location": "mem_0x938caf9b340087ab", 
                    "size": "0x8", 
                    "value": "0xa9b6172ad4b1f5e8"
                }, 
                "4": {
                    "location": "mem_0x8ad627f17ab8abf3", 
                    "size": "0x8", 
                    "value": "0xffffffffa53e8e56"
                }
            }
        }, 
        "43": {
            "inputs": {
                "0": {
                    "location": "RBP", 
                    "size": "0x8", 
                    "value": "0x4325c3080c611672"
                }, 
                "1": {
                    "location": "mem_0x0", 
                    "size": "0x8", 
                    "value": "0x87fe7ff39ce9d98d"
                }, 
                "2": {
                    "location": "mem_0x1", 
                    "size": "0x8", 
                    "value": "0x221da6e671129c58"
                }, 
                "3": {
                    "location": "mem_0x2", 
                    "size": "0x4", 
                    "value": "0x8c965544"
                }
            }, 
            "outputs": {
                "0": {
                    "location": "RAX", 
                    "size": "0x8", 
                    "value": "0x221da6e671129c58"
                }, 
                "1": {
                    "location": "EAX", 
                    "size": "0x4", 
                    "value": "0x71129c58"
                }, 
                "2": {
                    "location": "RDX", 
                    "size": "0x8", 
                    "value": "0xffffffff8c965544"
                }, 
                "3": {
                    "location": "mem_0x4325c3080c6108b2", 
                    "size": "0x8", 
                    "value": "0x87fe7ff39ce9d98e"
                }, 
                "4": {
                    "location": "mem_0x221da6e671129c58", 
                    "size": "0x8", 
                    "value": "0xffffffff8c965544"
                }
            }
        }, 
        "44": {
            "inputs": {
                "0": {
                    "location": "RBP", 
                    "size": "0x8", 
                    "value": "0xd85caf1507c7e737"
                }, 
                "1": {
                    "location": "mem_0x0", 
                    "size": "0x8", 
                    "value": "0x7c16d7c93b9317b6"
                }, 
                "2": {
                    "location": "mem_0x1", 
                    "size": "0x8", 
                    "value": "0xac05450ceb43e254"
                }, 
                "3": {
                    "location": "mem_0x2", 
                    "size": "0x4", 
                    "value": "0xbfba06a0"
                }
            }, 
            "outputs": {
                "0": {
                    "location": "RAX", 
                    "size": "0x8", 
                    "value": "0xac05450ceb43e254"
                }, 
                "1": {
                    "location": "EAX", 
                    "size": "0x4", 
                    "value": "0xeb43e254"
                }, 
                "2": {
                    "location": "RDX", 
                    "size": "0x8", 
                    "value": "0xffffffffbfba06a0"
                }, 
                "3": {
                    "location": "mem_0xd85caf1507c7d977", 
                    "size": "0x8", 
                    "value": "0x7c16d7c93b9317b7"
                }, 
                "4": {
                    "location": "mem_0xac05450ceb43e254", 
                    "size": "0x8", 
                    "value": "0xffffffffbfba06a0"
                }
            }
        }, 
        "45": {
            "inputs": {
                "0": {
                    "location": "RBP", 
                    "size": "0x8", 
                    "value": "0x4916a8ea544407de"
                }, 
                "1": {
                    "location": "mem_0x0", 
                    "size": "0x8", 
                    "value": "0x10d8ce02969d1c84"
                }, 
                "2": {
                    "location": "mem_0x1", 
                    "size": "0x8", 
                    "value": "0x3def4de55f09088d"
                }, 
                "3": {
                    "location": "mem_0x2", 
                    "size": "0x4", 
                    "value": "0xc1b29545"
                }
            }, 
            "outputs": {
                "0": {
                    "location": "RAX", 
                    "size": "0x8", 
                    "value": "0x3def4de55f09088d"
                }, 
                "1": {
                    "location": "EAX", 
                    "size": "0x4", 
                    "value": "0x5f09088d"
                }, 
                "2": {
                    "location": "RDX", 
                    "size": "0x8", 
                    "value": "0xffffffffc1b29545"
                }, 
                "3": {
                    "location": "mem_0x4916a8ea5443fa1e", 
                    "size": "0x8", 
                    "value": "0x10d8ce02969d1c85"
                }, 
                "4": {
                    "location": "mem_0x3def4de55f09088d", 
                    "size": "0x8", 
                    "value": "0xffffffffc1b29545"
                }
            }
        }, 
        "46": {
            "inputs": {
                "0": {
                    "location": "RBP", 
                    "size": "0x8", 
                    "value": "0x5b676563e1e5d480"
                }, 
                "1": {
                    "location": "mem_0x0", 
                    "size": "0x8", 
                    "value": "0x47697a104bdf3892"
                }, 
                "2": {
                    "location": "mem_0x1", 
                    "size": "0x8", 
                    "value": "0xb4bc124071ef5f30"
                }, 
                "3": {
                    "location": "mem_0x2", 
                    "size": "0x4", 
                    "value": "0x66e04c3b"
                }
            }, 
            "outputs": {
                "0": {
                    "location": "RAX", 
                    "size": "0x8", 
                    "value": "0xb4bc124071ef5f30"
                }, 
                "1": {
                    "location": "EAX", 
                    "size": "0x4", 
                    "value": "0x71ef5f30"
                }, 
                "2": {
                    "location": "RDX", 
                    "size": "0x8", 
                    "value": "0x66e04c3b"
                }, 
                "3": {
                    "location": "mem_0x5b676563e1e5c6c0", 
                    "size": "0x8", 
                    "value": "0x47697a104bdf3893"
                }, 
                "4": {
                    "location": "mem_0xb4bc124071ef5f30", 
                    "size": "0x8", 
                    "value": "0x66e04c3b"
                }
            }
        }, 
        "47": {
            "inputs": {
                "0": {
                    "location": "RBP", 
                    "size": "0x8", 
                    "value": "0x489d9529779cc788"
                }, 
                "1": {
                    "location": "mem_0x0", 
                    "size": "0x8", 
                    "value": "0xda95d2acf0335cb6"
                }, 
                "2": {
                    "location": "mem_0x1", 
                    "size": "0x8", 
                    "value": "0x844509db7950537b"
                }, 
                "3": {
                    "location": "mem_0x2", 
                    "size": "0x4", 
                    "value": "0x6dee5aa"
                }
            }, 
            "outputs": {
                "0": {
                    "location": "RAX", 
                    "size": "0x8", 
                    "value": "0x844509db7950537b"
                }, 
                "1": {
                    "location": "EAX", 
                    "size": "0x4", 
                    "value": "0x7950537b"
                }, 
                "2": {
                    "location": "RDX", 
                    "size": "0x8", 
                    "value": "0x6dee5aa"
                }, 
                "3": {
                    "location": "mem_0x489d9529779cb9c8", 
                    "size": "0x8", 
                    "value": "0xda95d2acf0335cb7"
                }, 
                "4": {
                    "location": "mem_0x844509db7950537b", 
                    "size": "0x8", 
                    "value": "0x6dee5aa"
                }
            }
        }, 
        "48": {
            "inputs": {
                "0": {
                    "location": "RBP", 
                    "size": "0x8", 
                    "value": "0x29e39cc19e17d30f"
                }, 
                "1": {
                    "location": "mem_0x0", 
                    "size": "0x8", 
                    "value": "0xa4b369cef62fbc2c"
                }, 
                "2": {
                    "location": "mem_0x1", 
                    "size": "0x8", 
                    "value": "0xef69efa5d6076143"
                }, 
                "3": {
                    "location": "mem_0x2", 
                    "size": "0x4", 
                    "value": "0x852a5068"
                }
            }, 
            "outputs": {
                "0": {
                    "location": "RAX", 
                    "size": "0x8", 
                    "value": "0xef69efa5d6076143"
                }, 
                "1": {
                    "location": "EAX", 
                    "size": "0x4", 
                    "value": "0xd6076143"
                }, 
                "2": {
                    "location": "RDX", 
                    "size": "0x8", 
                    "value": "0xffffffff852a5068"
                }, 
                "3": {
                    "location": "mem_0x29e39cc19e17c54f", 
                    "size": "0x8", 
                    "value": "0xa4b369cef62fbc2d"
                }, 
                "4": {
                    "location": "mem_0xef69efa5d6076143", 
                    "size": "0x8", 
                    "value": "0xffffffff852a5068"
                }
            }
        }, 
        "49": {
            "inputs": {
                "0": {
                    "location": "RBP", 
                    "size": "0x8", 
                    "value": "0x867b914915306279"
                }, 
                "1": {
                    "location": "mem_0x0", 
                    "size": "0x8", 
                    "value": "0xb304f33fccf39158"
                }, 
                "2": {
                    "location": "mem_0x1", 
                    "size": "0x8", 
                    "value": "0x4eadf5c6860054fa"
                }, 
                "3": {
                    "location": "mem_0x2", 
                    "size": "0x4", 
                    "value": "0x7271ecf8"
                }
            }, 
            "outputs": {
                "0": {
                    "location": "RAX", 
                    "size": "0x8", 
                    "value": "0x4eadf5c6860054fa"
                }, 
                "1": {
                    "location": "EAX", 
                    "size": "0x4", 
                    "value": "0x860054fa"
                }, 
                "2": {
                    "location": "RDX", 
                    "size": "0x8", 
                    "value": "0x7271ecf8"
                }, 
                "3": {
                    "location": "mem_0x867b9149153054b9", 
                    "size": "0x8", 
                    "value": "0xb304f33fccf39159"
                }, 
                "4": {
                    "location": "mem_0x4eadf5c6860054fa", 
                    "size": "0x8", 
                    "value": "0x7271ecf8"
                }
            }
        }
    }
}