{
    "initial": {
        "inputs": {
            "0": {
                "location": "RSP", 
                "size": "0x8", 
                "value": "0xac956cf776731ddb"
            }
        }, 
        "outputs": {
            "0": {
                "location": "RSP", 
                "size": "0x8", 
                "value": "0xac956cf776731dd3"
            }, 
            "1": {
                "location": "mem_0xac956cf776731dd3", 
                "size": "0x8", 
                "value": "0x1000005"
            }
        }
    }, 
    "sampling": {
        "0": {
            "inputs": {
                "0": {
                    "location": "RSP", 
                    "size": "0x8", 
                    "value": "0x5eee8602e8c41b9f"
                }
            }, 
            "outputs": {
                "0": {
                    "location": "RSP", 
                    "size": "0x8", 
                    "value": "0x5eee8602e8c41b97"
                }, 
                "1": {
                    "location": "mem_0x5eee8602e8c41b97", 
                    "size": "0x8", 
                    "value": "0x1000005"
                }
            }
        }, 
        "1": {
            "inputs": {
                "0": {
                    "location": "RSP", 
                    "size": "0x8", 
                    "value": "0xffa05b0f5f33c2e0"
                }
            }, 
            "outputs": {
                "0": {
                    "location": "RSP", 
                    "size": "0x8", 
                    "value": "0xffa05b0f5f33c2d8"
                }, 
                "1": {
                    "location": "mem_0xffa05b0f5f33c2d8", 
                    "size": "0x8", 
                    "value": "0x1000005"
                }
            }
        }, 
        "2": {
            "inputs": {
                "0": {
                    "location": "RSP", 
                    "size": "0x8", 
                    "value": "0x19b2769bf71a7ccf"
                }
            }, 
            "outputs": {
                "0": {
                    "location": "RSP", 
                    "size": "0x8", 
                    "value": "0x19b2769bf71a7cc7"
                }, 
                "1": {
                    "location": "mem_0x19b2769bf71a7cc7", 
                    "size": "0x8", 
                    "value": "0x1000005"
                }
            }
        }, 
        "3": {
            "inputs": {
                "0": {
                    "location": "RSP", 
                    "size": "0x8", 
                    "value": "0xf022da1f364bb8d3"
                }
            }, 
            "outputs": {
                "0": {
                    "location": "RSP", 
                    "size": "0x8", 
                    "value": "0xf022da1f364bb8cb"
                }, 
                "1": {
                    "location": "mem_0xf022da1f364bb8cb", 
                    "size": "0x8", 
                    "value": "0x1000005"
                }
            }
        }, 
        "4": {
            "inputs": {
                "0": {
                    "location": "RSP", 
                    "size": "0x8", 
                    "value": "0xb303764fe67a23c9"
                }
            }, 
            "outputs": {
                "0": {
                    "location": "RSP", 
                    "size": "0x8", 
                    "value": "0xb303764fe67a23c1"
                }, 
                "1": {
                    "location": "mem_0xb303764fe67a23c1", 
                    "size": "0x8", 
                    "value": "0x1000005"
                }
            }
        }, 
        "5": {
            "inputs": {
                "0": {
                    "location": "RSP", 
                    "size": "0x8", 
                    "value": "0xdc4518bedd779867"
                }
            }, 
            "outputs": {
                "0": {
                    "location": "RSP", 
                    "size": "0x8", 
                    "value": "0xdc4518bedd77985f"
                }, 
                "1": {
                    "location": "mem_0xdc4518bedd77985f", 
                    "size": "0x8", 
                    "value": "0x1000005"
                }
            }
        }, 
        "6": {
            "inputs": {
                "0": {
                    "location": "RSP", 
                    "size": "0x8", 
                    "value": "0x28b752b31fb49fd8"
                }
            }, 
            "outputs": {
                "0": {
                    "location": "RSP", 
                    "size": "0x8", 
                    "value": "0x28b752b31fb49fd0"
                }, 
                "1": {
                    "location": "mem_0x28b752b31fb49fd0", 
                    "size": "0x8", 
                    "value": "0x1000005"
                }
            }
        }, 
        "7": {
            "inputs": {
                "0": {
                    "location": "RSP", 
                    "size": "0x8", 
                    "value": "0x7cd279b5736149d1"
                }
            }, 
            "outputs": {
                "0": {
                    "location": "RSP", 
                    "size": "0x8", 
                    "value": "0x7cd279b5736149c9"
                }, 
                "1": {
                    "location": "mem_0x7cd279b5736149c9", 
                    "size": "0x8", 
                    "value": "0x1000005"
                }
            }
        }, 
        "8": {
            "inputs": {
                "0": {
                    "location": "RSP", 
                    "size": "0x8", 
                    "value": "0xf29851c8d0327865"
                }
            }, 
            "outputs": {
                "0": {
                    "location": "RSP", 
                    "size": "0x8", 
                    "value": "0xf29851c8d032785d"
                }, 
                "1": {
                    "location": "mem_0xf29851c8d032785d", 
                    "size": "0x8", 
                    "value": "0x1000005"
                }
            }
        }, 
        "9": {
            "inputs": {
                "0": {
                    "location": "RSP", 
                    "size": "0x8", 
                    "value": "0xac266860bec045fd"
                }
            }, 
            "outputs": {
                "0": {
                    "location": "RSP", 
                    "size": "0x8", 
                    "value": "0xac266860bec045f5"
                }, 
                "1": {
                    "location": "mem_0xac266860bec045f5", 
                    "size": "0x8", 
                    "value": "0x1000005"
                }
            }
        }, 
        "10": {
            "inputs": {
                "0": {
                    "location": "RSP", 
                    "size": "0x8", 
                    "value": "0xfff474f541327406"
                }
            }, 
            "outputs": {
                "0": {
                    "location": "RSP", 
                    "size": "0x8", 
                    "value": "0xfff474f5413273fe"
                }, 
                "1": {
                    "location": "mem_0xfff474f5413273fe", 
                    "size": "0x8", 
                    "value": "0x1000005"
                }
            }
        }, 
        "11": {
            "inputs": {
                "0": {
                    "location": "RSP", 
                    "size": "0x8", 
                    "value": "0x1a1a88070505e202"
                }
            }, 
            "outputs": {
                "0": {
                    "location": "RSP", 
                    "size": "0x8", 
                    "value": "0x1a1a88070505e1fa"
                }, 
                "1": {
                    "location": "mem_0x1a1a88070505e1fa", 
                    "size": "0x8", 
                    "value": "0x1000005"
                }
            }
        }, 
        "12": {
            "inputs": {
                "0": {
                    "location": "RSP", 
                    "size": "0x8", 
                    "value": "0x1214875238a353f9"
                }
            }, 
            "outputs": {
                "0": {
                    "location": "RSP", 
                    "size": "0x8", 
                    "value": "0x1214875238a353f1"
                }, 
                "1": {
                    "location": "mem_0x1214875238a353f1", 
                    "size": "0x8", 
                    "value": "0x1000005"
                }
            }
        }, 
        "13": {
            "inputs": {
                "0": {
                    "location": "RSP", 
                    "size": "0x8", 
                    "value": "0x7722781b311b5c5e"
                }
            }, 
            "outputs": {
                "0": {
                    "location": "RSP", 
                    "size": "0x8", 
                    "value": "0x7722781b311b5c56"
                }, 
                "1": {
                    "location": "mem_0x7722781b311b5c56", 
                    "size": "0x8", 
                    "value": "0x1000005"
                }
            }
        }, 
        "14": {
            "inputs": {
                "0": {
                    "location": "RSP", 
                    "size": "0x8", 
                    "value": "0xa0a2f3c3118e0598"
                }
            }, 
            "outputs": {
                "0": {
                    "location": "RSP", 
                    "size": "0x8", 
                    "value": "0xa0a2f3c3118e0590"
                }, 
                "1": {
                    "location": "mem_0xa0a2f3c3118e0590", 
                    "size": "0x8", 
                    "value": "0x1000005"
                }
            }
        }, 
        "15": {
            "inputs": {
                "0": {
                    "location": "RSP", 
                    "size": "0x8", 
                    "value": "0x25c4ced9c9582e91"
                }
            }, 
            "outputs": {
                "0": {
                    "location": "RSP", 
                    "size": "0x8", 
                    "value": "0x25c4ced9c9582e89"
                }, 
                "1": {
                    "location": "mem_0x25c4ced9c9582e89", 
                    "size": "0x8", 
                    "value": "0x1000005"
                }
            }
        }, 
        "16": {
            "inputs": {
                "0": {
                    "location": "RSP", 
                    "size": "0x8", 
                    "value": "0xd35ff236fefd7465"
                }
            }, 
            "outputs": {
                "0": {
                    "location": "RSP", 
                    "size": "0x8", 
                    "value": "0xd35ff236fefd745d"
                }, 
                "1": {
                    "location": "mem_0xd35ff236fefd745d", 
                    "size": "0x8", 
                    "value": "0x1000005"
                }
            }
        }, 
        "17": {
            "inputs": {
                "0": {
                    "location": "RSP", 
                    "size": "0x8", 
                    "value": "0xc91e09fa9255df0a"
                }
            }, 
            "outputs": {
                "0": {
                    "location": "RSP", 
                    "size": "0x8", 
                    "value": "0xc91e09fa9255df02"
                }, 
                "1": {
                    "location": "mem_0xc91e09fa9255df02", 
                    "size": "0x8", 
                    "value": "0x1000005"
                }
            }
        }, 
        "18": {
            "inputs": {
                "0": {
                    "location": "RSP", 
                    "size": "0x8", 
                    "value": "0xc363dd5e30e7f319"
                }
            }, 
            "outputs": {
                "0": {
                    "location": "RSP", 
                    "size": "0x8", 
                    "value": "0xc363dd5e30e7f311"
                }, 
                "1": {
                    "location": "mem_0xc363dd5e30e7f311", 
                    "size": "0x8", 
                    "value": "0x1000005"
                }
            }
        }, 
        "19": {
            "inputs": {
                "0": {
                    "location": "RSP", 
                    "size": "0x8", 
                    "value": "0x1049d8dea3f1f6df"
                }
            }, 
            "outputs": {
                "0": {
                    "location": "RSP", 
                    "size": "0x8", 
                    "value": "0x1049d8dea3f1f6d7"
                }, 
                "1": {
                    "location": "mem_0x1049d8dea3f1f6d7", 
                    "size": "0x8", 
                    "value": "0x1000005"
                }
            }
        }, 
        "20": {
            "inputs": {
                "0": {
                    "location": "RSP", 
                    "size": "0x8", 
                    "value": "0xde70aa0250695467"
                }
            }, 
            "outputs": {
                "0": {
                    "location": "RSP", 
                    "size": "0x8", 
                    "value": "0xde70aa025069545f"
                }, 
                "1": {
                    "location": "mem_0xde70aa025069545f", 
                    "size": "0x8", 
                    "value": "0x1000005"
                }
            }
        }, 
        "21": {
            "inputs": {
                "0": {
                    "location": "RSP", 
                    "size": "0x8", 
                    "value": "0x85aa1515beb67192"
                }
            }, 
            "outputs": {
                "0": {
                    "location": "RSP", 
                    "size": "0x8", 
                    "value": "0x85aa1515beb6718a"
                }, 
                "1": {
                    "location": "mem_0x85aa1515beb6718a", 
                    "size": "0x8", 
                    "value": "0x1000005"
                }
            }
        }, 
        "22": {
            "inputs": {
                "0": {
                    "location": "RSP", 
                    "size": "0x8", 
                    "value": "0x99faf98d6651f0d6"
                }
            }, 
            "outputs": {
                "0": {
                    "location": "RSP", 
                    "size": "0x8", 
                    "value": "0x99faf98d6651f0ce"
                }, 
                "1": {
                    "location": "mem_0x99faf98d6651f0ce", 
                    "size": "0x8", 
                    "value": "0x1000005"
                }
            }
        }, 
        "23": {
            "inputs": {
                "0": {
                    "location": "RSP", 
                    "size": "0x8", 
                    "value": "0xac5d8412447b6d94"
                }
            }, 
            "outputs": {
                "0": {
                    "location": "RSP", 
                    "size": "0x8", 
                    "value": "0xac5d8412447b6d8c"
                }, 
                "1": {
                    "location": "mem_0xac5d8412447b6d8c", 
                    "size": "0x8", 
                    "value": "0x1000005"
                }
            }
        }, 
        "24": {
            "inputs": {
                "0": {
                    "location": "RSP", 
                    "size": "0x8", 
                    "value": "0xa198e9d72bd76404"
                }
            }, 
            "outputs": {
                "0": {
                    "location": "RSP", 
                    "size": "0x8", 
                    "value": "0xa198e9d72bd763fc"
                }, 
                "1": {
                    "location": "mem_0xa198e9d72bd763fc", 
                    "size": "0x8", 
                    "value": "0x1000005"
                }
            }
        }, 
        "25": {
            "inputs": {
                "0": {
                    "location": "RSP", 
                    "size": "0x8", 
                    "value": "0xe2e45945cf0eb7f7"
                }
            }, 
            "outputs": {
                "0": {
                    "location": "RSP", 
                    "size": "0x8", 
                    "value": "0xe2e45945cf0eb7ef"
                }, 
                "1": {
                    "location": "mem_0xe2e45945cf0eb7ef", 
                    "size": "0x8", 
                    "value": "0x1000005"
                }
            }
        }, 
        "26": {
            "inputs": {
                "0": {
                    "location": "RSP", 
                    "size": "0x8", 
                    "value": "0x1545c9cbe4ae65bd"
                }
            }, 
            "outputs": {
                "0": {
                    "location": "RSP", 
                    "size": "0x8", 
                    "value": "0x1545c9cbe4ae65b5"
                }, 
                "1": {
                    "location": "mem_0x1545c9cbe4ae65b5", 
                    "size": "0x8", 
                    "value": "0x1000005"
                }
            }
        }, 
        "27": {
            "inputs": {
                "0": {
                    "location": "RSP", 
                    "size": "0x8", 
                    "value": "0x329362d7c2f5d65a"
                }
            }, 
            "outputs": {
                "0": {
                    "location": "RSP", 
                    "size": "0x8", 
                    "value": "0x329362d7c2f5d652"
                }, 
                "1": {
                    "location": "mem_0x329362d7c2f5d652", 
                    "size": "0x8", 
                    "value": "0x1000005"
                }
            }
        }, 
        "28": {
            "inputs": {
                "0": {
                    "location": "RSP", 
                    "size": "0x8", 
                    "value": "0x9fec9dc3a257a19d"
                }
            }, 
            "outputs": {
                "0": {
                    "location": "RSP", 
                    "size": "0x8", 
                    "value": "0x9fec9dc3a257a195"
                }, 
                "1": {
                    "location": "mem_0x9fec9dc3a257a195", 
                    "size": "0x8", 
                    "value": "0x1000005"
                }
            }
        }, 
        "29": {
            "inputs": {
                "0": {
                    "location": "RSP", 
                    "size": "0x8", 
                    "value": "0x1b7ec3eebef92965"
                }
            }, 
            "outputs": {
                "0": {
                    "location": "RSP", 
                    "size": "0x8", 
                    "value": "0x1b7ec3eebef9295d"
                }, 
                "1": {
                    "location": "mem_0x1b7ec3eebef9295d", 
                    "size": "0x8", 
                    "value": "0x1000005"
                }
            }
        }, 
        "30": {
            "inputs": {
                "0": {
                    "location": "RSP", 
                    "size": "0x8", 
                    "value": "0x8861aca42fc71e03"
                }
            }, 
            "outputs": {
                "0": {
                    "location": "RSP", 
                    "size": "0x8", 
                    "value": "0x8861aca42fc71dfb"
                }, 
                "1": {
                    "location": "mem_0x8861aca42fc71dfb", 
                    "size": "0x8", 
                    "value": "0x1000005"
                }
            }
        }, 
        "31": {
            "inputs": {
                "0": {
                    "location": "RSP", 
                    "size": "0x8", 
                    "value": "0xa423c42558dba541"
                }
            }, 
            "outputs": {
                "0": {
                    "location": "RSP", 
                    "size": "0x8", 
                    "value": "0xa423c42558dba539"
                }, 
                "1": {
                    "location": "mem_0xa423c42558dba539", 
                    "size": "0x8", 
                    "value": "0x1000005"
                }
            }
        }, 
        "32": {
            "inputs": {
                "0": {
                    "location": "RSP", 
                    "size": "0x8", 
                    "value": "0xe4c10c7435c6d9e1"
                }
            }, 
            "outputs": {
                "0": {
                    "location": "RSP", 
                    "size": "0x8", 
                    "value": "0xe4c10c7435c6d9d9"
                }, 
                "1": {
                    "location": "mem_0xe4c10c7435c6d9d9", 
                    "size": "0x8", 
                    "value": "0x1000005"
                }
            }
        }, 
        "33": {
            "inputs": {
                "0": {
                    "location": "RSP", 
                    "size": "0x8", 
                    "value": "0x528b5f34b3be6eb1"
                }
            }, 
            "outputs": {
                "0": {
                    "location": "RSP", 
                    "size": "0x8", 
                    "value": "0x528b5f34b3be6ea9"
                }, 
                "1": {
                    "location": "mem_0x528b5f34b3be6ea9", 
                    "size": "0x8", 
                    "value": "0x1000005"
                }
            }
        }, 
        "34": {
            "inputs": {
                "0": {
                    "location": "RSP", 
                    "size": "0x8", 
                    "value": "0x53836a9450eaefaf"
                }
            }, 
            "outputs": {
                "0": {
                    "location": "RSP", 
                    "size": "0x8", 
                    "value": "0x53836a9450eaefa7"
                }, 
                "1": {
                    "location": "mem_0x53836a9450eaefa7", 
                    "size": "0x8", 
                    "value": "0x1000005"
                }
            }
        }, 
        "35": {
            "inputs": {
                "0": {
                    "location": "RSP", 
                    "size": "0x8", 
                    "value": "0xe4b7fd6e416b70a8"
                }
            }, 
            "outputs": {
                "0": {
                    "location": "RSP", 
                    "size": "0x8", 
                    "value": "0xe4b7fd6e416b70a0"
                }, 
                "1": {
                    "location": "mem_0xe4b7fd6e416b70a0", 
                    "size": "0x8", 
                    "value": "0x1000005"
                }
            }
        }, 
        "36": {
            "inputs": {
                "0": {
                    "location": "RSP", 
                    "size": "0x8", 
                    "value": "0xf9f4e4020186b6d9"
                }
            }, 
            "outputs": {
                "0": {
                    "location": "RSP", 
                    "size": "0x8", 
                    "value": "0xf9f4e4020186b6d1"
                }, 
                "1": {
                    "location": "mem_0xf9f4e4020186b6d1", 
                    "size": "0x8", 
                    "value": "0x1000005"
                }
            }
        }, 
        "37": {
            "inputs": {
                "0": {
                    "location": "RSP", 
                    "size": "0x8", 
                    "value": "0xdfc69b71d9ee687d"
                }
            }, 
            "outputs": {
                "0": {
                    "location": "RSP", 
                    "size": "0x8", 
                    "value": "0xdfc69b71d9ee6875"
                }, 
                "1": {
                    "location": "mem_0xdfc69b71d9ee6875", 
                    "size": "0x8", 
                    "value": "0x1000005"
                }
            }
        }, 
        "38": {
            "inputs": {
                "0": {
                    "location": "RSP", 
                    "size": "0x8", 
                    "value": "0xeb5b9f439c7390ff"
                }
            }, 
            "outputs": {
                "0": {
                    "location": "RSP", 
                    "size": "0x8", 
                    "value": "0xeb5b9f439c7390f7"
                }, 
                "1": {
                    "location": "mem_0xeb5b9f439c7390f7", 
                    "size": "0x8", 
                    "value": "0x1000005"
                }
            }
        }, 
        "39": {
            "inputs": {
                "0": {
                    "location": "RSP", 
                    "size": "0x8", 
                    "value": "0x81b65addc126cad9"
                }
            }, 
            "outputs": {
                "0": {
                    "location": "RSP", 
                    "size": "0x8", 
                    "value": "0x81b65addc126cad1"
                }, 
                "1": {
                    "location": "mem_0x81b65addc126cad1", 
                    "size": "0x8", 
                    "value": "0x1000005"
                }
            }
        }, 
        "40": {
            "inputs": {
                "0": {
                    "location": "RSP", 
                    "size": "0x8", 
                    "value": "0xce9b24dfce76ff74"
                }
            }, 
            "outputs": {
                "0": {
                    "location": "RSP", 
                    "size": "0x8", 
                    "value": "0xce9b24dfce76ff6c"
                }, 
                "1": {
                    "location": "mem_0xce9b24dfce76ff6c", 
                    "size": "0x8", 
                    "value": "0x1000005"
                }
            }
        }, 
        "41": {
            "inputs": {
                "0": {
                    "location": "RSP", 
                    "size": "0x8", 
                    "value": "0xfa44382fdc92b6a3"
                }
            }, 
            "outputs": {
                "0": {
                    "location": "RSP", 
                    "size": "0x8", 
                    "value": "0xfa44382fdc92b69b"
                }, 
                "1": {
                    "location": "mem_0xfa44382fdc92b69b", 
                    "size": "0x8", 
                    "value": "0x1000005"
                }
            }
        }, 
        "42": {
            "inputs": {
                "0": {
                    "location": "RSP", 
                    "size": "0x8", 
                    "value": "0x98041ffa432d3da6"
                }
            }, 
            "outputs": {
                "0": {
                    "location": "RSP", 
                    "size": "0x8", 
                    "value": "0x98041ffa432d3d9e"
                }, 
                "1": {
                    "location": "mem_0x98041ffa432d3d9e", 
                    "size": "0x8", 
                    "value": "0x1000005"
                }
            }
        }, 
        "43": {
            "inputs": {
                "0": {
                    "location": "RSP", 
                    "size": "0x8", 
                    "value": "0x736ec96416fb71be"
                }
            }, 
            "outputs": {
                "0": {
                    "location": "RSP", 
                    "size": "0x8", 
                    "value": "0x736ec96416fb71b6"
                }, 
                "1": {
                    "location": "mem_0x736ec96416fb71b6", 
                    "size": "0x8", 
                    "value": "0x1000005"
                }
            }
        }, 
        "44": {
            "inputs": {
                "0": {
                    "location": "RSP", 
                    "size": "0x8", 
                    "value": "0x5224e53f10bf14ff"
                }
            }, 
            "outputs": {
                "0": {
                    "location": "RSP", 
                    "size": "0x8", 
                    "value": "0x5224e53f10bf14f7"
                }, 
                "1": {
                    "location": "mem_0x5224e53f10bf14f7", 
                    "size": "0x8", 
                    "value": "0x1000005"
                }
            }
        }, 
        "45": {
            "inputs": {
                "0": {
                    "location": "RSP", 
                    "size": "0x8", 
                    "value": "0x6a7575e1f80bf370"
                }
            }, 
            "outputs": {
                "0": {
                    "location": "RSP", 
                    "size": "0x8", 
                    "value": "0x6a7575e1f80bf368"
                }, 
                "1": {
                    "location": "mem_0x6a7575e1f80bf368", 
                    "size": "0x8", 
                    "value": "0x1000005"
                }
            }
        }, 
        "46": {
            "inputs": {
                "0": {
                    "location": "RSP", 
                    "size": "0x8", 
                    "value": "0x21da595d13134ad4"
                }
            }, 
            "outputs": {
                "0": {
                    "location": "RSP", 
                    "size": "0x8", 
                    "value": "0x21da595d13134acc"
                }, 
                "1": {
                    "location": "mem_0x21da595d13134acc", 
                    "size": "0x8", 
                    "value": "0x1000005"
                }
            }
        }, 
        "47": {
            "inputs": {
                "0": {
                    "location": "RSP", 
                    "size": "0x8", 
                    "value": "0x1c8cca4af3239adc"
                }
            }, 
            "outputs": {
                "0": {
                    "location": "RSP", 
                    "size": "0x8", 
                    "value": "0x1c8cca4af3239ad4"
                }, 
                "1": {
                    "location": "mem_0x1c8cca4af3239ad4", 
                    "size": "0x8", 
                    "value": "0x1000005"
                }
            }
        }, 
        "48": {
            "inputs": {
                "0": {
                    "location": "RSP", 
                    "size": "0x8", 
                    "value": "0x250769998ea4def5"
                }
            }, 
            "outputs": {
                "0": {
                    "location": "RSP", 
                    "size": "0x8", 
                    "value": "0x250769998ea4deed"
                }, 
                "1": {
                    "location": "mem_0x250769998ea4deed", 
                    "size": "0x8", 
                    "value": "0x1000005"
                }
            }
        }, 
        "49": {
            "inputs": {
                "0": {
                    "location": "RSP", 
                    "size": "0x8", 
                    "value": "0xa238aa135432463b"
                }
            }, 
            "outputs": {
                "0": {
                    "location": "RSP", 
                    "size": "0x8", 
                    "value": "0xa238aa1354324633"
                }, 
                "1": {
                    "location": "mem_0xa238aa1354324633", 
                    "size": "0x8", 
                    "value": "0x1000005"
                }
            }
        }
    }
}